addftool/__init__.py
addftool/addf_portal.py
addftool/blob.py
addftool/broadcast_folder.py
addftool/sleep.py
addftool/sync.py
addftool/tool.py
addftool/util.py
addftool/deploy/__init__.py
addftool/deploy/azure.py
addftool/deploy/ssh_server.py
addftool/deploy/vscode_server.py
addftool/process/__init__.py
addftool/process/utils.py
addftool/ssh/__init__.py
addftool-0.2.15.dist-info/METADATA
addftool-0.2.15.dist-info/WHEEL
addftool-0.2.15.dist-info/entry_points.txt
addftool-0.2.15.dist-info/top_level.txt
addftool-0.2.15.dist-info/RECORD
