Metadata-Version: 2.4
Name: addftool
Version: 0.2.15
Requires-Dist: cryptography
Requires-Dist: requests
Requires-Dist: PyYAML
Requires-Dist: psutil
Requires-Dist: fabric
Requires-Dist: gevent
Requires-Dist: parallel-ssh
